instant_python/__init__.py
instant_python/cli/__init__.py
instant_python/cli/cli.py
instant_python/cli/instant_python_typer.py
instant_python/config/__init__.py
instant_python/config/application/__init__.py
instant_python/config/application/config_generator.py
instant_python/config/delivery/__init__.py
instant_python/config/delivery/cli.py
instant_python/config/domain/__init__.py
instant_python/config/domain/question_wizard.py
instant_python/config/infra/__init__.py
instant_python/config/infra/question_wizard/__init__.py
instant_python/config/infra/question_wizard/questionary_console_wizard.py
instant_python/config/infra/question_wizard/step/__init__.py
instant_python/config/infra/question_wizard/step/dependencies_step.py
instant_python/config/infra/question_wizard/step/general_step.py
instant_python/config/infra/question_wizard/step/git_step.py
instant_python/config/infra/question_wizard/step/questionary.py
instant_python/config/infra/question_wizard/step/steps.py
instant_python/config/infra/question_wizard/step/template_step.py
instant_python/initialize/__init__.py
instant_python/initialize/application/__init__.py
instant_python/initialize/application/project_initializer.py
instant_python/initialize/delivery/__init__.py
instant_python/initialize/delivery/cli.py
instant_python/initialize/domain/__init__.py
instant_python/initialize/domain/env_manager.py
instant_python/initialize/domain/node.py
instant_python/initialize/domain/project_formatter.py
instant_python/initialize/domain/project_renderer.py
instant_python/initialize/domain/project_structure.py
instant_python/initialize/domain/project_writer.py
instant_python/initialize/domain/version_control_configurer.py
instant_python/initialize/infra/__init__.py
instant_python/initialize/infra/env_manager/__init__.py
instant_python/initialize/infra/env_manager/env_manager_factory.py
instant_python/initialize/infra/env_manager/pdm_env_manager.py
instant_python/initialize/infra/env_manager/system_console.py
instant_python-0.21.0.dist-info/METADATA
instant_python-0.21.0.dist-info/WHEEL
instant_python-0.21.0.dist-info/entry_points.txt
instant_python-0.21.0.dist-info/licenses/LICENSE
instant_python-0.21.0.dist-info/RECORD
