Metadata-Version: 2.4
Name: instant-python
Version: 0.21.0
Summary: Instant boilerplate generation for Python projects
Project-URL: documentation, https://dimanu-py.github.io/instant-python/
Project-URL: repository, https://github.com/dimanu-py/instant-python/
Author-email: dimanu-py <dimanu.py@gmail.com>
License:                                  Apache License
License-File: LICENSE
Classifier: Environment :: Console
Classifier: Intended Audience :: Developers
Classifier: Operating System :: MacOS
Classifier: Operating System :: Microsoft :: Windows
Classifier: Operating System :: POSIX :: Linux
Classifier: Operating System :: Unix
Classifier: Topic :: Software Development :: Code Generators
Classifier: Topic :: Software Development :: Libraries
Classifier: Topic :: Software Development :: Libraries :: Python Modules
Classifier: Topic :: System :: Installation/Setup
Classifier: Topic :: System :: Shells
Requires-Python: >=3.9
Requires-Dist: jinja2>=3.1.6
Requires-Dist: platformdirs>=4.4.0
Requires-Dist: posthog>=6.9.3
Requires-Dist: pydantic-settings>=2.11.0
Requires-Dist: pyyaml>=6.0.2
Requires-Dist: questionary>=2.1.0
Requires-Dist: typer>=0.15.1
Provides-Extra: build
Requires-Dist: uv>=0.7.21; extra == 'build'
